alpacagen/__init__.py
alpacagen/main.py
alpacagen/converters/__init__.py
alpacagen/converters/text.py
alpacagen/generators/__init__.py
alpacagen/generators/chunk.py
alpacagen/generators/dataset.py
alpacagen/generators/qa.py
alpacagen/models/__init__.py
alpacagen/models/qa_pair.py
alpacagen/prompt/__init__.py
alpacagen/prompt/prompt_gen_en.txt
alpacagen/prompt/prompt_gen_zhtw.txt
alpacagen/strategies/__init__.py
alpacagen/strategies/chunk.py
alpacagen-1.1.1.dist-info/LICENSE
alpacagen-1.1.1.dist-info/METADATA
alpacagen-1.1.1.dist-info/WHEEL
alpacagen-1.1.1.dist-info/top_level.txt
alpacagen-1.1.1.dist-info/RECORD
