Metadata-Version: 2.1
Name: alpacagen
Version: 1.1.1
Summary: A tool for generating instruction-following datasets in Alpaca format
Home-page: https://github.com/qqandy/alpacagen
Author: Hsiang-An Chuang
Author-email: Hsiang-An Chuang <qqandy0120@gmail.com>
License: MIT License
Project-URL: Homepage, https://github.com/qqandy0120/alpacagen
Project-URL: Repository, https://github.com/qqandy0120/alpacagen.git
Requires-Python: >=3.8
License-File: LICENSE
Requires-Dist: markitdown
Requires-Dist: langchain_text_splitters
Requires-Dist: openai>=1.0.0
Requires-Dist: tqdm
Requires-Dist: nest_asyncio
Provides-Extra: dev
Requires-Dist: pytest; extra == "dev"
Requires-Dist: pytest-mock; extra == "dev"
Requires-Dist: pytest-asyncio; extra == "dev"
